[
  {
    "username": "Volcaryx",
    "totalSolved": 206,
    "difficultyStats": {
      "easy": 95,
      "medium": 75,
      "hard": 36
    },
    "topicProgress": {
      "Arrays": {
        "solved": 19,
        "total": 53,
        "percentage": 36
      },
      "Matrix": {
        "solved": 2,
        "total": 6,
        "percentage": 33
      },
      "String": {
        "solved": 22,
        "total": 43,
        "percentage": 51
      },
      "Searching & Sorting": {
        "solved": 17,
        "total": 36,
        "percentage": 47
      },
      "Linked List": {
        "solved": 12,
        "total": 31,
        "percentage": 39
      },
      "Binary Trees": {
        "solved": 17,
        "total": 39,
        "percentage": 44
      },
      "Binary Search Trees": {
        "solved": 9,
        "total": 22,
        "percentage": 41
      },
      "Greedy": {
        "solved": 6,
        "total": 15,
        "percentage": 40
      },
      "Backtracking": {
        "solved": 9,
        "total": 19,
        "percentage": 47
      },
      "Stacks and Queues": {
        "solved": 10,
        "total": 23,
        "percentage": 43
      },
      "Heap": {
        "solved": 6,
        "total": 12,
        "percentage": 50
      },
      "Graph": {
        "solved": 23,
        "total": 54,
        "percentage": 43
      },
      "Trie": {
        "solved": 2,
        "total": 7,
        "percentage": 29
      },
      "Dynamic Programming": {
        "solved": 32,
        "total": 60,
        "percentage": 53
      },
      "Binary Search": {
        "solved": 15,
        "total": 35,
        "percentage": 43
      }
    },
    "lastUpdated": "2025-07-24T09:43:34.056Z"
  },
  {
    "username": "aagnesh",
    "totalSolved": 0,
    "difficultyStats": {
      "easy": 0,
      "medium": 0,
      "hard": 0
    },
    "topicProgress": {},
    "lastUpdated": "2025-07-24T09:43:36.131Z"
  },
  {
    "username": "dinesh",
    "totalSolved": 0,
    "difficultyStats": {
      "easy": 0,
      "medium": 0,
      "hard": 0
    },
    "topicProgress": {},
    "lastUpdated": "2025-07-24T09:43:38.206Z"
  }
]